{
  "generatedAt": "2026-04-23T08:25:20.540Z",
  "source": "static-snapshot",
  "analytics": {
    "totalPageviews": 18,
    "last7DaysPageviews": 18,
    "latestPageviewAt": "2026-04-22 07:40:48",
    "topPage": "/",
    "topPageViews": 0,
    "caseStudyCount": 3,
    "contentHistoryCount": 5,
    "staticMode": true,
    "snapshotGeneratedAt": "2026-04-23T08:25:20.540Z"
  },
  "caseStudies": [
    {
      "id": 1,
      "slug": "dngws-monitor",
      "badge": "CASE_01 // SIGNAL",
      "title": "DNGWS Monitor",
      "status": "live",
      "regionCode": "global",
      "location": "Global / multi-theater",
      "client": "Strategic intelligence operators",
      "sector": "Geopolitics + macro signal",
      "stakeholder": "Strategic operators and advisory rooms",
      "deploymentWindow": "Rapid live demo -> production monitoring surface",
      "decisionSurface": "Escalation tracking, spillover risk, and cross-source narrative compression.",
      "summary": "A working surface for geopolitical monitoring built for people who do not have time for PowerPoint latency.",
      "note": "The system keeps the room focused on a narrowing set of actions instead of a widening pile of feeds.",
      "outcome": "One monitoring surface replaced fragmented feed-checking and sharpened escalation briefings.",
      "evidenceType": "monitor",
      "evidenceSourceLabel": "Live system",
      "evidenceSourceUrl": "https://globalmonitor.fly.dev/",
      "confidenceScore": 0.93,
      "languageCoverage": "en,th,zh",
      "artifactCount": 12,
      "lastVerifiedAt": "2026-04-19 17:20:00",
      "linkLabel": "Open live system",
      "linkUrl": "https://globalmonitor.fly.dev/",
      "proofOrder": 1,
      "translations": {
        "th": {
          "title": "DNGWS Monitor",
          "stakeholder": "ทีมปฏิบัติการเชิงยุทธศาสตร์และห้องที่ปรึกษา",
          "deploymentWindow": "จากเดโมสดอย่างรวดเร็วสู่ระบบติดตามใช้งานจริง",
          "decisionSurface": "ใช้ติดตามความเสี่ยงการยกระดับ ความเสี่ยงลุกลาม และสรุปสัญญาณจากหลายแหล่งให้สั้นลง",
          "summary": "พื้นผิวการติดตามภูมิรัฐศาสตร์ที่ใช้งานได้จริง สำหรับคนที่ไม่มีเวลารอ PowerPoint",
          "note": "ระบบนี้ช่วยให้การสนทนาโฟกัสกับทางเลือกที่แคบลง แทนที่จะจมอยู่กับฟีดที่กระจายออกไป",
          "outcome": "หน้าจอติดตามเดียวแทนการเช็กหลายฟีดแยกกัน และช่วยให้การสรุปสถานการณ์คมขึ้น",
          "evidenceSourceLabel": "ระบบที่เปิดใช้งานจริง",
          "linkLabel": "เปิดระบบจริง"
        },
        "zh": {
          "title": "DNGWS Monitor",
          "stakeholder": "战略运营团队与顾问决策室",
          "deploymentWindow": "从快速现场演示到正式监测系统",
          "decisionSurface": "用于跟踪升级风险、外溢风险，并把多来源叙事压缩成可操作判断",
          "summary": "一个真正可用的地缘政治监测界面，服务于没有时间等待幻灯片的人",
          "note": "它让会议聚焦于更少但更重要的行动，而不是越来越多的资讯流",
          "outcome": "一个监测界面取代了分散的多路信息检查，并让升级简报更聚焦",
          "evidenceSourceLabel": "在线系统",
          "linkLabel": "打开在线系统"
        }
      },
      "metrics": [
        {
          "value": "12+",
          "label": "Open and operational sources compressed into one live surface",
          "metricOrder": 1
        },
        {
          "value": "LIVE",
          "label": "Continuous monitoring for escalation and spillover tracking",
          "metricOrder": 2
        },
        {
          "value": "GLOBAL",
          "label": "Multi-theater view across conflict, economy, and narrative",
          "metricOrder": 3
        },
        {
          "value": "45m",
          "label": "Field demo speed referenced in launch and press coverage",
          "metricOrder": 4
        }
      ]
    },
    {
      "id": 2,
      "slug": "phuket-dashboard",
      "badge": "CASE_02 // STREET",
      "title": "Phuket Dashboard",
      "status": "pilot",
      "regionCode": "thailand",
      "location": "Phuket, Thailand",
      "client": "Governor-grade regional operations",
      "sector": "Urban operations + transit + safety",
      "stakeholder": "Provincial command and regional operators",
      "deploymentWindow": "Pilot dashboard -> operational command room",
      "decisionSurface": "Transit telemetry, public safety, and environmental signals in one governor-facing view.",
      "summary": "A regional command layer that cuts city operations down to the few decisions the room actually needs to make fast.",
      "note": "The product logic is simple: use the existing data, compress the decision, and keep the interface awake enough for live operations.",
      "outcome": "Transit, safety, and environmental inputs were compressed into one governor-facing operating room.",
      "evidenceType": "operations",
      "evidenceSourceLabel": "Governor war room",
      "evidenceSourceUrl": "https://nonarkara.github.io/phuket-dashboard/war-room",
      "confidenceScore": 0.88,
      "languageCoverage": "en,th,zh",
      "artifactCount": 8,
      "lastVerifiedAt": "2026-04-19 17:20:00",
      "linkLabel": "Open live system",
      "linkUrl": "https://nonarkara.github.io/phuket-dashboard/war-room",
      "proofOrder": 2,
      "translations": {
        "th": {
          "title": "Phuket Dashboard",
          "stakeholder": "ศูนย์สั่งการระดับจังหวัดและผู้ปฏิบัติการระดับภูมิภาค",
          "deploymentWindow": "จากแดชบอร์ดนำร่องสู่ห้องปฏิบัติการสั่งการ",
          "decisionSurface": "รวมข้อมูลการขนส่ง ความปลอดภัยสาธารณะ และสิ่งแวดล้อมไว้ในมุมมองเดียวสำหรับผู้ว่าฯ",
          "summary": "ชั้นบัญชาการระดับภูมิภาคที่ย่อการปฏิบัติการเมืองให้เหลือเฉพาะการตัดสินใจที่ต้องทำทันที",
          "note": "ตรรกะของผลิตภัณฑ์เรียบง่าย: ใช้ข้อมูลที่มีอยู่ ย่อการตัดสินใจ และทำให้อินเทอร์เฟซพร้อมสำหรับงานสด",
          "outcome": "ข้อมูลขนส่ง ความปลอดภัย และสิ่งแวดล้อมถูกรวมเป็นห้องปฏิบัติการเดียวสำหรับผู้ว่าฯ",
          "evidenceSourceLabel": "ห้องวอร์รูมผู้ว่าฯ",
          "linkLabel": "เปิดระบบจริง"
        },
        "zh": {
          "title": "Phuket Dashboard",
          "stakeholder": "府级指挥中心与区域运营团队",
          "deploymentWindow": "从试点仪表盘到实际指挥室",
          "decisionSurface": "把交通遥测、公共安全与环境信号放进同一个面向省长的界面",
          "summary": "一个区域指挥层，把城市运营压缩成会议室真正需要快速决定的少数事项",
          "note": "产品逻辑很简单：使用现有数据，压缩决策路径，让界面随时可用于现场运营",
          "outcome": "交通、安全与环境输入被压缩进同一间面向省级领导的运行室",
          "evidenceSourceLabel": "省长作战室",
          "linkLabel": "打开在线系统"
        }
      },
      "metrics": [
        {
          "value": "42ms",
          "label": "Browser-side ping reference captured on the homepage health layer",
          "metricOrder": 1
        },
        {
          "value": "3.2k",
          "label": "Sensor and device count represented in the flagship ops room story",
          "metricOrder": 2
        },
        {
          "value": "REAL-TIME",
          "label": "Live telemetry architecture instead of static reporting",
          "metricOrder": 3
        },
        {
          "value": "REGIONAL",
          "label": "Governor-grade operating surface, not a brochure dashboard",
          "metricOrder": 4
        }
      ]
    },
    {
      "id": 3,
      "slug": "smart-city-thailand-index",
      "badge": "CASE_03 // STATE",
      "title": "Smart City Thailand Index",
      "status": "launched",
      "regionCode": "thailand",
      "location": "Thailand / national programme",
      "client": "depa and candidate cities",
      "sector": "Public programme tracking + civic benchmarking",
      "stakeholder": "National programme teams and candidate cities",
      "deploymentWindow": "Public reference layer with live programme visibility",
      "decisionSurface": "Proposal tracking, programme legibility, and ranking logic that can survive scrutiny.",
      "summary": "A national smart city tracking surface that makes the programme legible and keeps the evidence visible.",
      "note": "This is the clearest proof of the Axiom stance that governance systems should make bureaucracy readable, not ceremonial.",
      "outcome": "A national programme became inspectable in public instead of hidden in slide decks and reporting loops.",
      "evidenceType": "index",
      "evidenceSourceLabel": "Public index",
      "evidenceSourceUrl": "https://nonarkara.github.io/smart-city-thailand-index/",
      "confidenceScore": 0.91,
      "languageCoverage": "en,th,zh",
      "artifactCount": 5,
      "lastVerifiedAt": "2026-04-19 17:20:00",
      "linkLabel": "Open live system",
      "linkUrl": "https://nonarkara.github.io/smart-city-thailand-index/",
      "proofOrder": 3,
      "translations": {
        "th": {
          "title": "Smart City Thailand Index",
          "stakeholder": "ทีมโครงการระดับชาติและเมืองผู้สมัคร",
          "deploymentWindow": "ชั้นอ้างอิงสาธารณะที่มองเห็นความคืบหน้าโครงการได้แบบสด",
          "decisionSurface": "ใช้ติดตามข้อเสนอ ความชัดเจนของโครงการ และตรรกะการจัดอันดับที่ตรวจสอบได้",
          "summary": "พื้นผิวติดตามโครงการสมาร์ตซิตี้ระดับชาติที่ทำให้โครงการอ่านได้และทำให้หลักฐานมองเห็นได้",
          "note": "นี่คือหลักฐานที่ชัดที่สุดของแนวคิด Axiom ว่าระบบกำกับดูแลควรทำให้ระบบราชการอ่านได้ ไม่ใช่เป็นเพียงพิธีกรรม",
          "outcome": "โครงการระดับชาติกลายเป็นสิ่งที่สาธารณะตรวจสอบได้ แทนที่จะซ่อนอยู่ในสไลด์และวงจรรายงาน",
          "evidenceSourceLabel": "ดัชนีสาธารณะ",
          "linkLabel": "เปิดระบบจริง"
        },
        "zh": {
          "title": "Smart City Thailand Index",
          "stakeholder": "国家项目团队与候选城市",
          "deploymentWindow": "具备实时项目可见性的公共参考层",
          "decisionSurface": "用于跟踪提案、提升项目可读性，并公开可经受审视的排名逻辑",
          "summary": "一个国家级智慧城市追踪界面，让项目更易理解，也让证据始终可见",
          "note": "这是 Axiom 立场最清晰的证明：治理系统应该让官僚流程可读，而不是只剩仪式感",
          "outcome": "一个国家项目从幻灯片和报告流程中走出来，变成公众可检查的表层",
          "evidenceSourceLabel": "公开指数",
          "linkLabel": "打开在线系统"
        }
      },
      "metrics": [
        {
          "value": "174",
          "label": "Cities indexed in the launch story and public ranking narrative",
          "metricOrder": 1
        },
        {
          "value": "53",
          "label": "Nations represented in the Taipei launch context around the index",
          "metricOrder": 2
        },
        {
          "value": "5",
          "label": "Livability pillars exposed to users instead of hidden weighting logic",
          "metricOrder": 3
        },
        {
          "value": "PUBLIC",
          "label": "Open programme surface designed to be defended in daylight",
          "metricOrder": 4
        }
      ]
    }
  ],
  "contentHistory": [
    {
      "id": 1,
      "source": "SCSE Taipei",
      "title": "Protocol Alpha launched in Taipei with live dashboards on stage.",
      "summary": "Keynote, field proof, and ranking logic were shown as working systems instead of concept art, reinforcing the ship-first discipline behind the stack.",
      "category": "Launch",
      "eventPeriod": "2026 Q1",
      "location": "Taipei",
      "url": "",
      "historyOrder": 1,
      "metadata": {},
      "status": "published",
      "artifactType": "keynote",
      "confidenceScore": 0.95,
      "proofNote": "Public keynote backed by on-stage screenshots and live demonstrations.",
      "translations": {
        "th": {
          "source": "SCSE Taipei",
          "title": "Protocol Alpha เปิดตัวที่ไทเปพร้อมแดชบอร์ดสดบนเวที",
          "summary": "คีย์โน้ต หลักฐานภาคสนาม และตรรกะการจัดอันดับถูกแสดงเป็นระบบที่ทำงานจริง ไม่ใช่งานคอนเซปต์",
          "category": "เปิดตัว",
          "eventPeriod": "ไตรมาส 1 ปี 2026",
          "proofNote": "คีย์โน้ตสาธารณะที่มีภาพหน้าจอและการสาธิตสดบนเวทีรองรับ"
        },
        "zh": {
          "source": "SCSE Taipei",
          "title": "Protocol Alpha 在台北发布，并在台上展示实时仪表盘",
          "summary": "主题演讲、现场证据与排名逻辑以可运行系统的形式出现，而不是概念图",
          "category": "发布",
          "eventPeriod": "2026年第一季度",
          "proofNote": "公开演讲由现场截图和实时演示支持"
        }
      }
    },
    {
      "id": 2,
      "source": "Smart City Thailand Index",
      "title": "National programme tracking became a public-facing reference surface.",
      "summary": "The index shifted from a static claim into a legible public layer where proposals, progress, and programme logic stayed visible.",
      "category": "Programme",
      "eventPeriod": "2025 Q4",
      "location": "Thailand",
      "url": "https://nonarkara.github.io/smart-city-thailand-index/",
      "historyOrder": 2,
      "metadata": {},
      "status": "published",
      "artifactType": "index",
      "confidenceScore": 0.9,
      "proofNote": "Public index surface and launch references remain accessible online.",
      "translations": {
        "th": {
          "source": "Smart City Thailand Index",
          "title": "การติดตามโครงการระดับชาติกลายเป็นพื้นผิวอ้างอิงสาธารณะ",
          "summary": "ดัชนีเปลี่ยนจากคำกล่าวอ้างแบบคงที่ไปสู่ชั้นสาธารณะที่อ่านได้ ซึ่งทำให้ข้อเสนอ ความคืบหน้า และตรรกะของโครงการยังคงมองเห็นได้",
          "category": "โครงการ",
          "eventPeriod": "ไตรมาส 4 ปี 2025",
          "proofNote": "ดัชนีสาธารณะและหลักฐานการเปิดตัวยังคงเปิดให้เข้าถึงทางออนไลน์"
        },
        "zh": {
          "source": "Smart City Thailand Index",
          "title": "国家项目跟踪成为一个面向公众的参考界面",
          "summary": "该指数从静态主张转变为一个可读的公共层，使提案、进展和项目逻辑持续可见",
          "category": "项目",
          "eventPeriod": "2025年第四季度",
          "proofNote": "公开指数界面与发布资料仍可在线访问"
        }
      }
    },
    {
      "id": 3,
      "source": "Phuket Dashboard",
      "title": "Governor dashboard field build tightened the city-room operating model.",
      "summary": "Transit telemetry, environmental signal, and public safety were compressed into one interface designed for live decision-making under pressure.",
      "category": "Deployment",
      "eventPeriod": "2025 Q4",
      "location": "Phuket",
      "url": "https://nonarkara.github.io/phuket-dashboard/war-room",
      "historyOrder": 3,
      "metadata": {},
      "status": "field",
      "artifactType": "operations",
      "confidenceScore": 0.87,
      "proofNote": "Working interface and operational screenshots demonstrate the field build.",
      "translations": {
        "th": {
          "source": "Phuket Dashboard",
          "title": "การสร้างแดชบอร์ดภาคสนามสำหรับผู้ว่าฯ ทำให้โมเดลห้องปฏิบัติการเมืองคมขึ้น",
          "summary": "ข้อมูลขนส่ง สัญญาณสิ่งแวดล้อม และความปลอดภัยสาธารณะถูกรวมไว้ในอินเทอร์เฟซเดียวที่ออกแบบมาสำหรับการตัดสินใจแบบสดภายใต้แรงกดดัน",
          "category": "ลงพื้นที่",
          "eventPeriod": "ไตรมาส 4 ปี 2025",
          "proofNote": "อินเทอร์เฟซที่ใช้งานได้จริงและภาพหน้าจอการปฏิบัติการยืนยันการทำงานภาคสนาม"
        },
        "zh": {
          "source": "Phuket Dashboard",
          "title": "省长仪表盘的现场构建，让城市运行室模型更加清晰",
          "summary": "交通遥测、环境信号与公共安全被压缩进同一个为高压下实时决策而设计的界面",
          "category": "部署",
          "eventPeriod": "2025年第四季度",
          "proofNote": "可运行界面与操作截图证明了现场构建过程"
        }
      }
    },
    {
      "id": 4,
      "source": "ASEAN Smart Cities Network",
      "title": "Cross-city benchmarking moved from presentation to usable regional layer.",
      "summary": "The ASEAN network work connected project tracking with SLIC benchmarking, turning regional collaboration into something navigable instead of ceremonial.",
      "category": "Regional",
      "eventPeriod": "2025 Q3",
      "location": "ASEAN",
      "url": "https://nonarkara.github.io/ascn-smart-cities-network/",
      "historyOrder": 4,
      "metadata": {},
      "status": "published",
      "artifactType": "network",
      "confidenceScore": 0.84,
      "proofNote": "Regional project layer and supporting materials remain published online.",
      "translations": {
        "th": {
          "source": "ASEAN Smart Cities Network",
          "title": "การเปรียบเทียบข้ามเมืองขยับจากงานนำเสนอไปสู่ชั้นภูมิภาคที่ใช้งานได้",
          "summary": "งานในเครือข่ายอาเซียนเชื่อมการติดตามโครงการเข้ากับเกณฑ์เปรียบเทียบ SLIC ทำให้ความร่วมมือระดับภูมิภาคใช้งานได้จริงมากกว่าพิธีกรรม",
          "category": "ภูมิภาค",
          "eventPeriod": "ไตรมาส 3 ปี 2025",
          "proofNote": "ชั้นข้อมูลระดับภูมิภาคและเอกสารประกอบยังเผยแพร่ออนไลน์"
        },
        "zh": {
          "source": "ASEAN Smart Cities Network",
          "title": "跨城市基准比较从展示材料变成了可用的区域层",
          "summary": "东盟网络工作把项目跟踪与 SLIC 基准比较连接起来，使区域协作从仪式转向可导航的工作层",
          "category": "区域",
          "eventPeriod": "2025年第三季度",
          "proofNote": "区域项目层与相关材料仍在线公开"
        }
      }
    },
    {
      "id": 5,
      "source": "Solomon Islands Workshop",
      "title": "Whole-of-government digital roadmap work proved the model outside the core home market.",
      "summary": "The workshop framed sovereign digital transformation as a practical systems journey, not an abstract modernization slogan.",
      "category": "Roadmap",
      "eventPeriod": "2025 Q2",
      "location": "Honiara",
      "url": "https://nonarkara.github.io/solomon-islands-workshop/#institutions",
      "historyOrder": 5,
      "metadata": {},
      "status": "published",
      "artifactType": "roadmap",
      "confidenceScore": 0.82,
      "proofNote": "Workshop materials and institutional framing remain available online.",
      "translations": {
        "th": {
          "source": "Solomon Islands Workshop",
          "title": "งานโรดแมปดิจิทัลทั้งภาครัฐพิสูจน์โมเดลนี้นอกตลาดหลัก",
          "summary": "เวิร์กชอปวางกรอบการเปลี่ยนผ่านดิจิทัลระดับรัฐให้เป็นเส้นทางของระบบที่ทำได้จริง ไม่ใช่เพียงคำขวัญเรื่องความทันสมัย",
          "category": "โรดแมป",
          "eventPeriod": "ไตรมาส 2 ปี 2025",
          "proofNote": "เอกสารเวิร์กชอปและกรอบสถาบันยังคงเข้าถึงได้ออนไลน์"
        },
        "zh": {
          "source": "Solomon Islands Workshop",
          "title": "全政府数字路线图工作在核心本土市场之外验证了这一模型",
          "summary": "该工作坊把主权数字化转型定义为一条务实的系统路径，而不是抽象的现代化口号",
          "category": "路线图",
          "eventPeriod": "2025年第二季度",
          "proofNote": "工作坊材料与制度框架仍可在线访问"
        }
      }
    }
  ]
}
